pyscribe/__init__.py
pyscribe/__main__.py
pyscribe/cli.py
pyscribe/errors.py
pyscribe/py.typed
pyscribe/transcriber.py
pyscribe/utils.py
pyscribest-1.2.1.dist-info/licenses/LICENSE
pyscribest-1.2.1.dist-info/WHEEL
pyscribest-1.2.1.dist-info/entry_points.txt
pyscribest-1.2.1.dist-info/METADATA
pyscribest-1.2.1.dist-info/RECORD
