Metadata-Version: 2.4
Name: pyscribest
Version: 1.2.1
Summary: Audio transcriber powered by the ElevenLabs Scribe AI model.
Keywords: transcription,lyrics,elevenlabs,audio,cli
Author: tooru
Author-email: tooru <tooru@tooru.mom>
License-Expression: MIT
License-File: LICENSE
Classifier: Programming Language :: Python
Classifier: Programming Language :: Python :: 3.8
Classifier: Programming Language :: Python :: 3.9
Classifier: Programming Language :: Python :: 3.10
Classifier: Programming Language :: Python :: 3.11
Classifier: Programming Language :: Python :: 3.12
Classifier: Programming Language :: Python :: 3.13
Classifier: Programming Language :: Python :: 3.14
Classifier: Operating System :: OS Independent
Classifier: License :: OSI Approved :: MIT License
Classifier: Intended Audience :: End Users/Desktop
Classifier: Topic :: Multimedia :: Sound/Audio :: Analysis
Requires-Dist: elevenlabs~=2.29.0
Requires-Dist: keyring>=25.5 ; extra == 'keyring'
Requires-Python: >=3.8
Project-URL: Issues, https://github.com/tooruu/pyscribe/issues
Project-URL: Repository, https://github.com/tooruu/pyscribe
Provides-Extra: keyring
